ds_util/__init__.py
ds_util/git.py
ds_util/notebook.py
ds_util/s3.py
ds_util/sample_command.py
ds_util-0.1.6.dist-info/METADATA
ds_util-0.1.6.dist-info/WHEEL
ds_util-0.1.6.dist-info/entry_points.txt
ds_util-0.1.6.dist-info/top_level.txt
ds_util-0.1.6.dist-info/RECORD
