Metadata-Version: 2.1
Name: ds-util
Version: 0.1.6
Summary: ds-util is a set of tools that are often used in data science projects.
Home-page: https://gitlab.nasa.future.co.jp/data-analysis/mlops/ds-util
Author: noko
Author-email: UNKNOWN
License: UNKNOWN
Platform: UNKNOWN
Classifier: Programming Language :: Python :: 3
Classifier: License :: OSI Approved :: MIT License
Classifier: Operating System :: OS Independent
Requires-Python: >=3.7
Requires-Dist: boto3
Requires-Dist: jupyter
